[
    {
        "data": [
            {
                "allowSdrSoftwareBrightness": false,
                "autoRotation": "InTabletMode",
                "brightness": 0.01,
                "colorPowerTradeoff": "PreferEfficiency",
                "colorProfileSource": "sRGB",
                "connectorName": "eDP-1",
                "edidHash": "aeb0bab93f7456c4de962c09685a1b76",
                "edidIdentifier": "CMN 5409 0 10 2020 0",
                "highDynamicRange": false,
                "iccProfilePath": "",
                "mode": {
                    "height": 1080,
                    "refreshRate": 59963,
                    "width": 1920
                },
                "overscan": 0,
                "rgbRange": "Automatic",
                "scale": 1,
                "sdrBrightness": 200,
                "sdrGamutWideness": 0,
                "transform": "Normal",
                "vrrPolicy": "Automatic",
                "wideColorGamut": false
            },
            {
                "allowSdrSoftwareBrightness": false,
                "autoRotation": "InTabletMode",
                "brightness": 0,
                "colorPowerTradeoff": "PreferEfficiency",
                "colorProfileSource": "sRGB",
                "connectorName": "HDMI-A-1",
                "edidHash": "ee9f45a7d72537949c609d439126b354",
                "edidIdentifier": "DEL 17101 851479683 21 2022 0",
                "highDynamicRange": false,
                "iccProfilePath": "",
                "mode": {
                    "height": 1080,
                    "refreshRate": 60000,
                    "width": 1920
                },
                "overscan": 0,
                "rgbRange": "Automatic",
                "scale": 1,
                "sdrBrightness": 200,
                "sdrGamutWideness": 0,
                "transform": "Normal",
                "vrrPolicy": "Automatic",
                "wideColorGamut": false
            },
            {
                "allowSdrSoftwareBrightness": false,
                "autoRotation": "InTabletMode",
                "brightness": 0.99,
                "colorProfileSource": "sRGB",
                "connectorName": "eDP-1",
                "edidHash": "0722b5431675c43cf9e7858f88d9f251",
                "edidIdentifier": "CMN 5120 0 47 2018 0",
                "highDynamicRange": false,
                "iccProfilePath": "",
                "mode": {
                    "height": 1080,
                    "refreshRate": 60008,
                    "width": 1920
                },
                "overscan": 0,
                "rgbRange": "Automatic",
                "scale": 1.25,
                "sdrBrightness": 200,
                "sdrGamutWideness": 0,
                "transform": "Normal",
                "vrrPolicy": "Automatic",
                "wideColorGamut": false
            },
            {
                "allowSdrSoftwareBrightness": false,
                "autoRotation": "InTabletMode",
                "brightness": 0.1,
                "colorPowerTradeoff": "PreferEfficiency",
                "colorProfileSource": "sRGB",
                "connectorName": "HDMI-A-1",
                "edidHash": "8bfcf93d361ab387b131daa3e6e3ddb7",
                "edidIdentifier": "DEL 17101 902405618 21 2022 0",
                "highDynamicRange": false,
                "iccProfilePath": "",
                "mode": {
                    "height": 1080,
                    "refreshRate": 60160,
                    "width": 1920
                },
                "overscan": 0,
                "rgbRange": "Automatic",
                "scale": 1,
                "sdrBrightness": 200,
                "sdrGamutWideness": 0,
                "transform": "Normal",
                "vrrPolicy": "Automatic",
                "wideColorGamut": false
            },
            {
                "allowSdrSoftwareBrightness": true,
                "autoRotation": "InTabletMode",
                "brightness": 1,
                "colorPowerTradeoff": "PreferEfficiency",
                "colorProfileSource": "sRGB",
                "connectorName": "Virtual-virtual-xdp-kde-librewolf",
                "highDynamicRange": false,
                "iccProfilePath": "",
                "mode": {
                    "height": 1080,
                    "refreshRate": 60000,
                    "width": 1920
                },
                "overscan": 0,
                "rgbRange": "Automatic",
                "scale": 1,
                "sdrBrightness": 200,
                "sdrGamutWideness": 0,
                "transform": "Normal",
                "vrrPolicy": "Automatic",
                "wideColorGamut": false
            },
            {
                "allowSdrSoftwareBrightness": false,
                "autoRotation": "InTabletMode",
                "brightness": 0.37401574803149606,
                "colorPowerTradeoff": "PreferEfficiency",
                "colorProfileSource": "sRGB",
                "connectorName": "eDP-1",
                "edidHash": "2be66912b35cd87f3c565aa28cd10617",
                "edidIdentifier": "SDC 16724 0 35 2020 0",
                "highDynamicRange": false,
                "iccProfilePath": "",
                "mode": {
                    "height": 1800,
                    "refreshRate": 90001,
                    "width": 2880
                },
                "overscan": 0,
                "rgbRange": "Automatic",
                "scale": 1.6,
                "sdrBrightness": 400,
                "sdrGamutWideness": 0,
                "transform": "Normal",
                "vrrPolicy": "Automatic",
                "wideColorGamut": false
            }
        ],
        "name": "outputs"
    },
    {
        "data": [
            {
                "lidClosed": false,
                "outputs": [
                    {
                        "enabled": true,
                        "outputIndex": 0,
                        "position": {
                            "x": 0,
                            "y": 0
                        },
                        "priority": 0
                    }
                ]
            },
            {
                "lidClosed": false,
                "outputs": [
                    {
                        "enabled": true,
                        "outputIndex": 1,
                        "position": {
                            "x": 0,
                            "y": 0
                        },
                        "priority": 0
                    }
                ]
            },
            {
                "lidClosed": true,
                "outputs": [
                    {
                        "enabled": true,
                        "outputIndex": 0,
                        "position": {
                            "x": 0,
                            "y": 0
                        },
                        "priority": 0
                    }
                ]
            },
            {
                "lidClosed": false,
                "outputs": [
                    {
                        "enabled": true,
                        "outputIndex": 2,
                        "position": {
                            "x": 0,
                            "y": 0
                        },
                        "priority": 0
                    }
                ]
            },
            {
                "lidClosed": false,
                "outputs": [
                    {
                        "enabled": true,
                        "outputIndex": 3,
                        "position": {
                            "x": 0,
                            "y": 0
                        },
                        "priority": 0
                    }
                ]
            },
            {
                "lidClosed": false,
                "outputs": [
                    {
                        "enabled": true,
                        "outputIndex": 0,
                        "position": {
                            "x": 0,
                            "y": 0
                        },
                        "priority": 0
                    },
                    {
                        "enabled": true,
                        "outputIndex": 4,
                        "position": {
                            "x": 1920,
                            "y": 0
                        },
                        "priority": 1
                    }
                ]
            },
            {
                "lidClosed": false,
                "outputs": [
                    {
                        "enabled": true,
                        "outputIndex": 5,
                        "position": {
                            "x": 0,
                            "y": 0
                        },
                        "priority": 0
                    }
                ]
            }
        ],
        "name": "setups"
    }
]
